[
  {
    "id": 1,
    "date": "27 дек 2025",
    "subject": "cs",
    "title": "Шпаргалка по методам строк в Python",
    "text": "Подготовил таблицу со всеми основными методами: .split(), .join()...",
    "image": "https://via.placeholder.com/800x400",
    "link": "#",
    "linkText": "Открыть изображение"
  },
  {
    "id": 2,
    "date": "25 дек 2025",
    "subject": "math",
    "title": "Тригонометрия: Формулы приведения",
    "text": "Разбор сложной темы. В файле — теория и 20 задач.",
    "file": {
      "name": "Trigonometry_Pack.pdf",
      "size": "2.4 MB",
      "url": "files/trigonometry.pdf"
    }
  },
   {
    "id": 3,
    "date": "28 дек 2025",
    "subject": "phys",
    "title": "Важная новость по ЕГЭ",
    "text": "⚛️ Задача ЕГЭ про искусственный спутник на круговой орбите.<br>  🔸 Удобная ассоциация: любое тело, находящееся на орбите планеты, все время падает на нее за счет центростремительного ускорения. Как правило, оно настолько мало, что некоторыми его параметрами можно просто пренебречь.",
    "image": "https://raw.githubusercontent.com/SwordBird2002/fizmat_materials/refs/heads/main/fiz1.jpg"
   }
]












